pyconstring/__init__.py
pyconstring/pyconstring.py
pyconstring-1.0.0.dist-info/DESCRIPTION.rst
pyconstring-1.0.0.dist-info/METADATA
pyconstring-1.0.0.dist-info/RECORD
pyconstring-1.0.0.dist-info/WHEEL
pyconstring-1.0.0.dist-info/metadata.json
pyconstring-1.0.0.dist-info/top_level.txt
pyconstring-1.0.0.dist-info/zip-safe
