Metadata-Version: 2.0
Name: pyconstring
Version: 1.0.0
Summary: Tool to handle connection strings
Home-page: https://github.com/bgusach/pyconstring
Author: Bor González-Usach
Author-email: bgusach@gmail.com
License: MIT
Keywords: connection string
Platform: UNKNOWN
Classifier: License :: OSI Approved :: MIT License
Classifier: Development Status :: 5 - Production/Stable
Classifier: Operating System :: OS Independent
Classifier: Topic :: Database
Classifier: Topic :: Utilities
